upyboard/__init__.py
upyboard/upy.py
upyboard/core/EFR32MG/src/utools.py
upyboard/core/EFR32MG/typehints/binascii.pyi
upyboard/core/EFR32MG/typehints/errno.pyi
upyboard/core/EFR32MG/typehints/hashlib.pyi
upyboard/core/EFR32MG/typehints/io.pyi
upyboard/core/EFR32MG/typehints/json.pyi
upyboard/core/EFR32MG/typehints/machine.pyi
upyboard/core/EFR32MG/typehints/math.pyi
upyboard/core/EFR32MG/typehints/micropython.pyi
upyboard/core/EFR32MG/typehints/network.pyi
upyboard/core/EFR32MG/typehints/os.pyi
upyboard/core/EFR32MG/typehints/select.pyi
upyboard/core/EFR32MG/typehints/socket.pyi
upyboard/core/EFR32MG/typehints/ssl.pyi
upyboard/core/EFR32MG/typehints/struct.pyi
upyboard/core/EFR32MG/typehints/sys.pyi
upyboard/core/EFR32MG/typehints/time.pyi
upyboard/core/EFR32MG/typehints/ubinascii.pyi
upyboard/core/EFR32MG/typehints/ucryptolib.pyi
upyboard/core/EFR32MG/typehints/uerrno.pyi
upyboard/core/EFR32MG/typehints/uhashlib.pyi
upyboard/core/EFR32MG/typehints/uio.pyi
upyboard/core/EFR32MG/typehints/ujson.pyi
upyboard/core/EFR32MG/typehints/umachine.pyi
upyboard/core/EFR32MG/typehints/uos.pyi
upyboard/core/EFR32MG/typehints/uselect.pyi
upyboard/core/EFR32MG/typehints/usocket.pyi
upyboard/core/EFR32MG/typehints/ussl.pyi
upyboard/core/EFR32MG/typehints/ustruct.pyi
upyboard/core/EFR32MG/typehints/utime.pyi
upyboard/core/EFR32MG/typehints/utools.pyi
upyboard/core/EFR32MG/typehints/digi/__init__.pyi
upyboard/core/EFR32MG/typehints/digi/ble.pyi
upyboard/core/EFR32MG/typehints/digi/cloud.pyi
upyboard/core/EFR32MG/typehints/digi/gnss.pyi
upyboard/core/EFR32MG/typehints/xbee/__init__.pyi
upyboard/core/EFR32MG/typehints/xbee/modem_status.pyi
upyboard/core/EFR32MG/typehints/xbee/relay.pyi
upyboard/core/RP2350/src/blynk.py
upyboard/core/RP2350/src/utools.py
upyboard/core/RP2350/src/umqtt/robust2.py
upyboard/core/RP2350/src/umqtt/simple2.py
upyboard/core/RP2350/typehints/_asyncio.pyi
upyboard/core/RP2350/typehints/_boot_fat.pyi
upyboard/core/RP2350/typehints/_onewire.pyi
upyboard-0.9.35.dist-info/licenses/LICENSE
upyboard-0.9.35.dist-info/METADATA
upyboard-0.9.35.dist-info/WHEEL
upyboard-0.9.35.dist-info/entry_points.txt
upyboard-0.9.35.dist-info/top_level.txt
upyboard-0.9.35.dist-info/RECORD
