Metadata-Version: 2.4
Name: upyboard
Version: 0.9.35
Summary: This is a CLI tool for MicroPython-based embedded systems.
Home-page: https://github.com/planxstudio/upyboard
Author: chanmin.park
Author-email: devcamp@gmail.com
Keywords: micropython,pyserial,genlib
Classifier: Programming Language :: Python :: 3
Classifier: License :: OSI Approved :: MIT License
Classifier: Operating System :: OS Independent
Requires-Python: >=3.10
License-File: LICENSE
Requires-Dist: click
Requires-Dist: pyserial
Requires-Dist: genlib
Requires-Dist: mpy-cross
Dynamic: author
Dynamic: author-email
Dynamic: classifier
Dynamic: description
Dynamic: description-content-type
Dynamic: home-page
Dynamic: keywords
Dynamic: license-file
Dynamic: requires-dist
Dynamic: requires-python
Dynamic: summary
